cafeteria/asyncio/callbacks.py
cafeteria/asyncio/commons.py
cafeteria/asyncio/patterns/application.py
cafeteria/asyncio/synchronous.py
cafeteria_asyncio-0.3.0.dist-info/LICENSE
cafeteria_asyncio-0.3.0.dist-info/METADATA
cafeteria_asyncio-0.3.0.dist-info/WHEEL
cafeteria_asyncio-0.3.0.dist-info/RECORD
