Metadata-Version: 2.1
Name: cafeteria-asyncio
Version: 0.3.0
Summary: An extension to the cafeteria package to enable asyncio specific patterns for python 3.7 and above applications/libraries.
Home-page: https://github.com/abn/cafeteria-asyncio
License: APLv2
Author: Arun Babu Neelicattu
Author-email: arun.neelicattu@gmail.com
Requires-Python: >=3.8,<4.0
Classifier: Framework :: AsyncIO
Classifier: Intended Audience :: Developers
Classifier: License :: OSI Approved :: Apache Software License
Classifier: License :: Other/Proprietary License
Classifier: Operating System :: OS Independent
Classifier: Programming Language :: Python :: 3
Classifier: Programming Language :: Python :: 3.8
Classifier: Programming Language :: Python :: 3.9
Classifier: Programming Language :: Python :: 3.10
Classifier: Programming Language :: Python :: 3.11
Classifier: Programming Language :: Python :: 3.12
Classifier: Topic :: Software Development :: Libraries :: Python Modules
Requires-Dist: cafeteria (>=0,<1,!=0.22.0)
Project-URL: Repository, https://github.com/abn/cafeteria-asyncio
